appconfigpy/__init__.py
appconfigpy/__version__.py
appconfigpy/_config.py
appconfigpy/_const.py
appconfigpy/_logger.py
appconfigpy/py.typed
examples/__init__.py
examples/common.py
examples/configure.py
examples/load.py
appconfigpy-2.0.1.dist-info/LICENSE
appconfigpy-2.0.1.dist-info/METADATA
appconfigpy-2.0.1.dist-info/WHEEL
appconfigpy-2.0.1.dist-info/top_level.txt
appconfigpy-2.0.1.dist-info/RECORD
